kelid/__init__.py
kelid/cli.py
kelid/core.py
kelid/setup.py
kelid/utils.py
kelid-2.7.4.dist-info/METADATA
kelid-2.7.4.dist-info/WHEEL
kelid-2.7.4.dist-info/entry_points.txt
kelid-2.7.4.dist-info/top_level.txt
kelid-2.7.4.dist-info/RECORD
