Metadata-Version: 2.4
Name: kelid
Version: 2.7.4
Summary: Kelid is a Python code locker using marshal and base64.
Home-page: https://github.com/iTs-GoJo/kelid
Author: Ali-Jafari
Author-email: thealiapi@gmail.com
Classifier: Programming Language :: Python :: 3
Classifier: License :: OSI Approved :: MIT License
Classifier: Operating System :: OS Independent
Requires-Python: >=3.6
Dynamic: author
Dynamic: author-email
Dynamic: classifier
Dynamic: description
Dynamic: description-content-type
Dynamic: home-page
Dynamic: requires-python
Dynamic: summary
